cloud_functions_utils/__init__.py
cloud_functions_utils/bigquery.py
cloud_functions_utils/error_reporting.py
cloud_functions_utils/exceptions.py
cloud_functions_utils/pub_sub.py
cloud_functions_utils/storage.py
cloud_functions_utils-0.5.0.dist-info/LICENSE
cloud_functions_utils-0.5.0.dist-info/WHEEL
cloud_functions_utils-0.5.0.dist-info/METADATA
cloud_functions_utils-0.5.0.dist-info/RECORD
